downall/__init__.py
downall/downall.py
downall-1.0.0.dist-info/LICENSE
downall-1.0.0.dist-info/METADATA
downall-1.0.0.dist-info/WHEEL
downall-1.0.0.dist-info/top_level.txt
downall-1.0.0.dist-info/RECORD
