Metadata-Version: 2.1
Name: downall
Version: 1.0.0
Summary: Library to download everything
Home-page: https://github.com/Game-K-Hack/DownAll
Author: Game K
Author-email: game_k@laposte.net
License: UNKNOWN
Project-URL: Bug Tracker, https://github.com/Game-K-Hack/DownAll/issues
Platform: UNKNOWN
Classifier: Programming Language :: Python :: 3
Classifier: License :: OSI Approved :: GNU General Public License (GPL)
Classifier: Operating System :: OS Independent
Requires-Python: >=3.6
License-File: LICENSE
